<PAMDataset>
  <PAMRasterBand band="1">
    <Histograms>
      <HistItem>
        <HistMin>-0.5</HistMin>
        <HistMax>100.5</HistMax>
        <BucketCount>101</BucketCount>
        <IncludeOutOfRange>1</IncludeOutOfRange>
        <Approximate>0</Approximate>
        <HistCounts>4197119|24|1096|3855|6215|7437|8729|9466|10200|11003|11673|12473|12894|13574|13377|13614|13478|13097|12740|12134|11621|11121|10609|9943|9672|9273|8864|8578|8220|8051|7965|7552|7542|7428|7328|7352|7274|7300|7407|7306|7273|7215|7305|7311|7291|7522|7562|7821|7851|8102|8477|8898|9098|9609|9800|10030|10272|10611|10899|11438|11964|12173|11759|12019|11769|11130|10535|9645|8851|7990|6973|5980|5020|4294|3862|3887|4004|4018|4123|4339|4505|4746|5222|5973|6998|7256|6750|5994|4765|3874|3137|2547|2021|1463|1075|736|525|317|218|85|13</HistCounts>
      </HistItem>
    </Histograms>
    <Metadata>
      <MDI key="STATISTICS_MINIMUM">0</MDI>
      <MDI key="STATISTICS_MAXIMUM">100</MDI>
      <MDI key="STATISTICS_MEAN">6.4901166181701</MDI>
      <MDI key="STATISTICS_STDDEV">18.091197065103</MDI>
      <MDI key="STATISTICS_MEDIAN">0.000000</MDI>
      <MDI key="STATISTICS_COUNT">4951544.000000</MDI>
      <MDI key="STATISTICS_SKIPFACTORX">1</MDI>
      <MDI key="STATISTICS_SKIPFACTORY">1</MDI>
      <MDI key="STATISTICS_EXCLUDEDVALUES"></MDI>
      <MDI key="STATISTICS_COVARIANCES">327.2914112484005</MDI>
    </Metadata>
  </PAMRasterBand>
</PAMDataset>
